la_coding_theory/__convolutional.py
la_coding_theory/__crc.py
la_coding_theory/__init__.py
la_coding_theory/__lrc.py
la_coding_theory/__vrc.py
la_coding_theory-0.0.4.dist-info/LICENCE
la_coding_theory-0.0.4.dist-info/METADATA
la_coding_theory-0.0.4.dist-info/WHEEL
la_coding_theory-0.0.4.dist-info/top_level.txt
la_coding_theory-0.0.4.dist-info/RECORD
